rtl/jtag_tap_fsm.sv
// jtag_tap_fsm.sv
// IEEE 1149.1 Test Access Port (TAP) controller state machine.
//
// 16-state FSM driven by TMS, sampled on the RISING edge of TCK.
// TRST_n is the optional asynchronous, active-low reset that forces the
// controller into Test-Logic-Reset (1149.1 also allows reaching this state
// by holding TMS high for 5 TCKs, which this FSM does naturally).
//
// This block is the Day-1 deliverable: state sequencing only. The decoded
// strobe outputs (capture_*, shift_*, update_*) are the hooks the IR/DR
// logic will hang off in Day 2.

module jtag_tap_fsm
  import jtag_pkg::*;
(
  input  logic       tck,       // test clock
  input  logic       trst_n,    // async active-low reset (optional in 1149.1)
  input  logic       tms,       // test mode select, sampled on posedge tck

  output tap_state_e state,     // current controller state

  // decoded control strobes for downstream IR/DR logic (used in Day 2)
  output logic       reset_n_int, // de-asserted (0) while in Test-Logic-Reset
  output logic       capture_dr,
  output logic       shift_dr,
  output logic       update_dr,
  output logic       capture_ir,
  output logic       shift_ir,
  output logic       update_ir
);

  tap_state_e next;

  // ---------------------------------------------------------------------
  // Next-state logic -- a direct transcription of the 1149.1 state diagram.
  // For each state: TMS=1 takes the "right/up" branch, TMS=0 the "down/left".
  // ---------------------------------------------------------------------
  always_comb begin
    // For each state: the first literal is the TMS=1 target, the second TMS=0.
    unique case (state)
      TEST_LOGIC_RESET : if (tms) next = TEST_LOGIC_RESET; else next = RUN_TEST_IDLE;
      RUN_TEST_IDLE    : if (tms) next = SELECT_DR_SCAN;   else next = RUN_TEST_IDLE;

      SELECT_DR_SCAN   : if (tms) next = SELECT_IR_SCAN;   else next = CAPTURE_DR;
      CAPTURE_DR       : if (tms) next = EXIT1_DR;         else next = SHIFT_DR;
      SHIFT_DR         : if (tms) next = EXIT1_DR;         else next = SHIFT_DR;
      EXIT1_DR         : if (tms) next = UPDATE_DR;        else next = PAUSE_DR;
      PAUSE_DR         : if (tms) next = EXIT2_DR;         else next = PAUSE_DR;
      EXIT2_DR         : if (tms) next = UPDATE_DR;        else next = SHIFT_DR;
      UPDATE_DR        : if (tms) next = SELECT_DR_SCAN;   else next = RUN_TEST_IDLE;

      SELECT_IR_SCAN   : if (tms) next = TEST_LOGIC_RESET; else next = CAPTURE_IR;
      CAPTURE_IR       : if (tms) next = EXIT1_IR;         else next = SHIFT_IR;
      SHIFT_IR         : if (tms) next = EXIT1_IR;         else next = SHIFT_IR;
      EXIT1_IR         : if (tms) next = UPDATE_IR;        else next = PAUSE_IR;
      PAUSE_IR         : if (tms) next = EXIT2_IR;         else next = PAUSE_IR;
      EXIT2_IR         : if (tms) next = UPDATE_IR;        else next = SHIFT_IR;
      UPDATE_IR        : if (tms) next = SELECT_DR_SCAN;   else next = RUN_TEST_IDLE;

      default          : next = TEST_LOGIC_RESET;
    endcase
  end

  // ---------------------------------------------------------------------
  // State register: TMS is sampled on the rising edge of TCK.
  // ---------------------------------------------------------------------
  always_ff @(posedge tck or negedge trst_n) begin
    if (!trst_n) state <= TEST_LOGIC_RESET;
    else         state <= next;
  end

  // ---------------------------------------------------------------------
  // Decoded outputs (combinational decode of current state).
  // ---------------------------------------------------------------------
  assign reset_n_int = (state != TEST_LOGIC_RESET);
  assign capture_dr  = (state == CAPTURE_DR);
  assign shift_dr    = (state == SHIFT_DR);
  assign update_dr   = (state == UPDATE_DR);
  assign capture_ir  = (state == CAPTURE_IR);
  assign shift_ir    = (state == SHIFT_IR);
  assign update_ir   = (state == UPDATE_IR);

endmodule : jtag_tap_fsm

tb/tb_jtag_tap_fsm.sv
// tb_jtag_tap_fsm.sv
// Directed, self-checking testbench for the 1149.1 TAP controller FSM.
//
// Strategy:
//   1. Async reset -> confirm Test-Logic-Reset.
//   2. Walk a 48-step TMS "tour" whose expected states are taken by hand
//      from the 1149.1 state diagram. The tour is constructed to traverse
//      every one of the 32 edges (16 states x 2 TMS values) at least once.
//      A coverage array records which edges were actually exercised and the
//      test FAILS if any edge is missed.
//   3. Confirm the "5 TMS-high TCKs forces Test-Logic-Reset" property.
//   4. Re-confirm async TRST_n from a deep state.

`timescale 1ns/1ps
module tb_jtag_tap_fsm;
  import jtag_pkg::*;

  logic       tck = 1'b0;
  logic       trst_n;
  logic       tms;
  tap_state_e state;
  logic       reset_n_int, capture_dr, shift_dr, update_dr;
  logic       capture_ir, shift_ir, update_ir;

  jtag_tap_fsm dut (
    .tck(tck), .trst_n(trst_n), .tms(tms), .state(state),
    .reset_n_int(reset_n_int),
    .capture_dr(capture_dr), .shift_dr(shift_dr), .update_dr(update_dr),
    .capture_ir(capture_ir), .shift_ir(shift_ir), .update_ir(update_ir)
  );

  int errors      = 0;
  int checks      = 0;
  bit covered [16][2];   // covered[from_state][tms]

  // .name() may only be called on an enum *variable* in Icarus, not on a
  // net/port, so wrap it: the function argument is a variable.
  function automatic string sname(input tap_state_e s);
    return s.name();
  endfunction

  // Apply one TCK cycle: set TMS, rising edge (state updates), then check.
  task automatic step(input logic tms_v, input tap_state_e exp);
    tap_state_e from;
    from = state;
    tms  = tms_v;
    #2 tck = 1'b1;        // rising edge -> state <= next
    #2;                   // settle
    covered[int'(from)][tms_v] = 1'b1;
    checks++;
    if (state !== exp) begin
      errors++;
      $display("  [FAIL] %0t  %-16s --tms=%0b--> got %-16s  expected %-16s",
               $time, sname(from), tms_v, sname(state), sname(exp));
    end else begin
      $display("  [ ok ] %-16s --tms=%0b--> %-16s", sname(from), tms_v, sname(state));
    end
    tck = 1'b0;
    #2;
  endtask

  // -------------------------------------------------------------------
  // 48-step tour. Each {tms, expected_state} pair is read off the spec.
  // Collectively these traverse all 32 edges (verified by coverage below).
  // -------------------------------------------------------------------
  logic       tour_tms [48];
  tap_state_e tour_exp [48];

  task automatic build_tour();
    int i; i = 0;
    `define S(T,E) begin tour_tms[i]=(T); tour_exp[i]=(E); i++; end
    `S(1, TEST_LOGIC_RESET)               //  1  TLR  stays
    `S(0, RUN_TEST_IDLE)                  //  2
    `S(0, RUN_TEST_IDLE)                  //  3  RTI  stays
    `S(1, SELECT_DR_SCAN)                 //  4
    `S(0, CAPTURE_DR)                     //  5
    `S(0, SHIFT_DR)                       //  6
    `S(0, SHIFT_DR)                       //  7  ShDR stays
    `S(1, EXIT1_DR)                       //  8
    `S(0, PAUSE_DR)                       //  9
    `S(0, PAUSE_DR)                       // 10  PauDR stays
    `S(1, EXIT2_DR)                       // 11
    `S(0, SHIFT_DR)                       // 12  Exit2->Shift
    `S(1, EXIT1_DR)                       // 13
    `S(1, UPDATE_DR)                      // 14
    `S(0, RUN_TEST_IDLE)                  // 15
    `S(1, SELECT_DR_SCAN)                 // 16
    `S(0, CAPTURE_DR)                     // 17
    `S(1, EXIT1_DR)                       // 18  Capture->Exit1
    `S(1, UPDATE_DR)                      // 19
    `S(1, SELECT_DR_SCAN)                 // 20  Update->Select-DR
    `S(1, SELECT_IR_SCAN)                 // 21
    `S(0, CAPTURE_IR)                     // 22
    `S(0, SHIFT_IR)                       // 23
    `S(0, SHIFT_IR)                       // 24  ShIR stays
    `S(1, EXIT1_IR)                       // 25
    `S(0, PAUSE_IR)                       // 26
    `S(0, PAUSE_IR)                       // 27  PauIR stays
    `S(1, EXIT2_IR)                       // 28
    `S(0, SHIFT_IR)                       // 29  Exit2->Shift
    `S(1, EXIT1_IR)                       // 30
    `S(1, UPDATE_IR)                      // 31
    `S(1, SELECT_DR_SCAN)                 // 32  Update-IR->Select-DR
    `S(1, SELECT_IR_SCAN)                 // 33
    `S(0, CAPTURE_IR)                     // 34
    `S(1, EXIT1_IR)                       // 35  Capture->Exit1
    `S(0, PAUSE_IR)                       // 36
    `S(1, EXIT2_IR)                       // 37
    `S(1, UPDATE_IR)                      // 38  Exit2->Update
    `S(0, RUN_TEST_IDLE)                  // 39  Update-IR->RTI
    `S(1, SELECT_DR_SCAN)                 // 40
    `S(0, CAPTURE_DR)                     // 41
    `S(1, EXIT1_DR)                       // 42
    `S(0, PAUSE_DR)                       // 43
    `S(1, EXIT2_DR)                       // 44
    `S(1, UPDATE_DR)                      // 45  Exit2->Update
    `S(1, SELECT_DR_SCAN)                 // 46
    `S(1, SELECT_IR_SCAN)                 // 47
    `S(1, TEST_LOGIC_RESET)              // 48  Select-IR->TLR
    `undef S
  endtask

  // -------------------------------------------------------------------
  // Test sequence
  // -------------------------------------------------------------------
  initial begin
    $dumpfile("sim/tap_fsm.vcd");
    $dumpvars(0, tb_jtag_tap_fsm);

    // ---- 1. Async reset ----
    tms    = 1'b1;
    trst_n = 1'b0;
    #5;
    if (state !== TEST_LOGIC_RESET) begin
      errors++; $display("  [FAIL] async TRST_n did not reach TEST_LOGIC_RESET (got %s)", sname(state));
    end else
      $display("  [ ok ] async TRST_n -> TEST_LOGIC_RESET");
    checks++;
    trst_n = 1'b1;
    #5;

    // ---- 2. Transition tour ----
    $display("\n-- transition tour (every edge of the 1149.1 diagram) --");
    build_tour();
    for (int k = 0; k < 48; k++) step(tour_tms[k], tour_exp[k]);

    // ---- 3. Edge-coverage check ----
    $display("\n-- edge coverage --");
    begin
      int hit; hit = 0;
      for (int s = 0; s < 16; s++)
        for (int t = 0; t < 2; t++)
          if (covered[s][t]) hit++;
          else begin
            errors++;
            $display("  [FAIL] edge never exercised: state=%0d tms=%0d", s, t);
          end
      $display("  edges covered: %0d / 32", hit);
    end

    // ---- 4. "5 TMS-high TCKs -> Test-Logic-Reset" from a deep state ----
    $display("\n-- 5x TMS-high forces reset --");
    // navigate TLR->RTI->SDR->CapDR->ShDR to get away from reset
    step(1, TEST_LOGIC_RESET); // from TLR, tms=1 stays in TLR
    step(0, RUN_TEST_IDLE);
    step(1, SELECT_DR_SCAN);
    step(0, CAPTURE_DR);
    step(0, SHIFT_DR);
    // now hold TMS high; reset is guaranteed within 5 cycles
    for (int k = 0; k < 5; k++) begin tms = 1'b1; #2 tck = 1'b1; #2 tck = 1'b0; #2; end
    checks++;
    if (state !== TEST_LOGIC_RESET) begin
      errors++; $display("  [FAIL] 5x TMS-high did not reach reset (got %s)", sname(state));
    end else
      $display("  [ ok ] 5x TMS-high -> TEST_LOGIC_RESET");

    // ---- summary ----
    $display("\n==================================================");
    $display(" checks run : %0d", checks);
    $display(" errors     : %0d", errors);
    if (errors == 0) $display(" RESULT     : PASS");
    else             $display(" RESULT     : FAIL");
    $display("==================================================");
    $finish;
  end

endmodule : tb_jtag_tap_fsm

sim/tap_fsm.vcd
$date
	Sat May 30 12:28:27 2026
$end
$version
	Icarus Verilog
$end
$timescale
	1ps
$end
$scope module tb_jtag_tap_fsm $end
$var wire 1 ! update_ir $end
$var wire 1 " update_dr $end
$var wire 4 # state [3:0] $end
$var wire 1 $ shift_ir $end
$var wire 1 % shift_dr $end
$var wire 1 & reset_n_int $end
$var wire 1 ' capture_ir $end
$var wire 1 ( capture_dr $end
$var reg 1 ) tck $end
$var reg 1 * tms $end
$var reg 1 + trst_n $end
$var integer 32 , checks [31:0] $end
$var integer 32 - errors [31:0] $end
$scope function sname $end
$upscope $end
$scope module dut $end
$var wire 1 ) tck $end
$var wire 1 * tms $end
$var wire 1 + trst_n $end
$var wire 1 ! update_ir $end
$var wire 1 " update_dr $end
$var wire 1 $ shift_ir $end
$var wire 1 % shift_dr $end
$var wire 1 & reset_n_int $end
$var wire 1 ' capture_ir $end
$var wire 1 ( capture_dr $end
$var reg 4 . next [3:0] $end
$var reg 4 / state [3:0] $end
$upscope $end
$scope begin $ivl_for_loop0 $end
$var integer 32 0 k [31:0] $end
$upscope $end
$scope begin $ivl_for_loop3 $end
$var integer 32 1 k [31:0] $end
$upscope $end
$scope begin $unm_blk_55 $end
$var integer 32 2 hit [31:0] $end
$scope begin $ivl_for_loop1 $end
$var integer 32 3 s [31:0] $end
$scope begin $ivl_for_loop2 $end
$var integer 32 4 t [31:0] $end
$upscope $end
$upscope $end
$upscope $end
$scope task build_tour $end
$upscope $end
$scope task step $end
$upscope $end
$upscope $end
$enddefinitions $end
$comment Show the parameter values. $end
$dumpall
$end
#0
$dumpvars
b0 4
b0 3
b0 2
b0 1
b0 0
b0 /
b0 .
b0 -
b0 ,
0+
1*
0)
0(
0'
0&
0%
0$
b0 #
0"
0!
$end
#5000
1+
b1 ,
#12000
1)
#14000
0)
b10 ,
#16000
b1 .
0*
b1 0
#18000
1&
b1 #
b1 /
1)
#20000
0)
b11 ,
#22000
b10 0
#24000
1)
#26000
0)
b100 ,
#28000
b10 .
1*
b11 0
#30000
b1001 .
b10 #
b10 /
1)
#32000
0)
b101 ,
#34000
b11 .
0*
b100 0
#36000
b100 .
1(
b11 #
b11 /
1)
#38000
0)
b110 ,
#40000
b101 0
#42000
0(
1%
b100 #
b100 /
1)
#44000
0)
b111 ,
#46000
b110 0
#48000
1)
#50000
0)
b1000 ,
#52000
b101 .
1*
b111 0
#54000
b1000 .
0%
b101 #
b101 /
1)
#56000
0)
b1001 ,
#58000
b110 .
0*
b1000 0
#60000
b110 #
b110 /
1)
#62000
0)
b1010 ,
#64000
b1001 0
#66000
1)
#68000
0)
b1011 ,
#70000
b111 .
1*
b1010 0
#72000
b1000 .
b111 #
b111 /
1)
#74000
0)
b1100 ,
#76000
b100 .
0*
b1011 0
#78000
1%
b100 #
b100 /
1)
#80000
0)
b1101 ,
#82000
b101 .
1*
b1100 0
#84000
b1000 .
0%
b101 #
b101 /
1)
#86000
0)
b1110 ,
#88000
b1101 0
#90000
b10 .
1"
b1000 #
b1000 /
1)
#92000
0)
b1111 ,
#94000
b1 .
0*
b1110 0
#96000
0"
b1 #
b1 /
1)
#98000
0)
b10000 ,
#100000
b10 .
1*
b1111 0
#102000
b1001 .
b10 #
b10 /
1)
#104000
0)
b10001 ,
#106000
b11 .
0*
b10000 0
#108000
b100 .
1(
b11 #
b11 /
1)
#110000
0)
b10010 ,
#112000
b101 .
1*
b10001 0
#114000
b1000 .
0(
b101 #
b101 /
1)
#116000
0)
b10011 ,
#118000
b10010 0
#120000
b10 .
1"
b1000 #
b1000 /
1)
#122000
0)
b10100 ,
#124000
b10011 0
#126000
b1001 .
0"
b10 #
b10 /
1)
#128000
0)
b10101 ,
#130000
b10100 0
#132000
b0 .
b1001 #
b1001 /
1)
#134000
0)
b10110 ,
#136000
b1010 .
0*
b10101 0
#138000
b1011 .
1'
b1010 #
b1010 /
1)
#140000
0)
b10111 ,
#142000
b10110 0
#144000
0'
1$
b1011 #
b1011 /
1)
#146000
0)
b11000 ,
#148000
b10111 0
#150000
1)
#152000
0)
b11001 ,
#154000
b1100 .
1*
b11000 0
#156000
b1111 .
0$
b1100 #
b1100 /
1)
#158000
0)
b11010 ,
#160000
b1101 .
0*
b11001 0
#162000
b1101 #
b1101 /
1)
#164000
0)
b11011 ,
#166000
b11010 0
#168000
1)
#170000
0)
b11100 ,
#172000
b1110 .
1*
b11011 0
#174000
b1111 .
b1110 #
b1110 /
1)
#176000
0)
b11101 ,
#178000
b1011 .
0*
b11100 0
#180000
1$
b1011 #
b1011 /
1)
#182000
0)
b11110 ,
#184000
b1100 .
1*
b11101 0
#186000
b1111 .
0$
b1100 #
b1100 /
1)
#188000
0)
b11111 ,
#190000
b11110 0
#192000
b10 .
1!
b1111 #
b1111 /
1)
#194000
0)
b100000 ,
#196000
b11111 0
#198000
b1001 .
0!
b10 #
b10 /
1)
#200000
0)
b100001 ,
#202000
b100000 0
#204000
b0 .
b1001 #
b1001 /
1)
#206000
0)
b100010 ,
#208000
b1010 .
0*
b100001 0
#210000
b1011 .
1'
b1010 #
b1010 /
1)
#212000
0)
b100011 ,
#214000
b1100 .
1*
b100010 0
#216000
b1111 .
0'
b1100 #
b1100 /
1)
#218000
0)
b100100 ,
#220000
b1101 .
0*
b100011 0
#222000
b1101 #
b1101 /
1)
#224000
0)
b100101 ,
#226000
b1110 .
1*
b100100 0
#228000
b1111 .
b1110 #
b1110 /
1)
#230000
0)
b100110 ,
#232000
b100101 0
#234000
b10 .
1!
b1111 #
b1111 /
1)
#236000
0)
b100111 ,
#238000
b1 .
0*
b100110 0
#240000
0!
b1 #
b1 /
1)
#242000
0)
b101000 ,
#244000
b10 .
1*
b100111 0
#246000
b1001 .
b10 #
b10 /
1)
#248000
0)
b101001 ,
#250000
b11 .
0*
b101000 0
#252000
b100 .
1(
b11 #
b11 /
1)
#254000
0)
b101010 ,
#256000
b101 .
1*
b101001 0
#258000
b1000 .
0(
b101 #
b101 /
1)
#260000
0)
b101011 ,
#262000
b110 .
0*
b101010 0
#264000
b110 #
b110 /
1)
#266000
0)
b101100 ,
#268000
b111 .
1*
b101011 0
#270000
b1000 .
b111 #
b111 /
1)
#272000
0)
b101101 ,
#274000
b101100 0
#276000
b10 .
1"
b1000 #
b1000 /
1)
#278000
0)
b101110 ,
#280000
b101101 0
#282000
b1001 .
0"
b10 #
b10 /
1)
#284000
0)
b101111 ,
#286000
b101110 0
#288000
b0 .
b1001 #
b1001 /
1)
#290000
0)
b110000 ,
#292000
b101111 0
#294000
0&
b0 #
b0 /
1)
#296000
0)
b110001 ,
#298000
b10000 3
b10 4
b100000 2
b110000 0
#300000
1)
#302000
0)
b110010 ,
#304000
b1 .
0*
#306000
1&
b1 #
b1 /
1)
#308000
0)
b110011 ,
#310000
b10 .
1*
#312000
b1001 .
b10 #
b10 /
1)
#314000
0)
b110100 ,
#316000
b11 .
0*
#318000
b100 .
1(
b11 #
b11 /
1)
#320000
0)
b110101 ,
#324000
0(
1%
b100 #
b100 /
1)
#326000
0)
b110110 ,
#328000
b101 .
1*
#330000
b1000 .
0%
b101 #
b101 /
1)
#332000
0)
#334000
b1 1
#336000
b10 .
1"
b1000 #
b1000 /
1)
#338000
0)
#340000
b10 1
#342000
b1001 .
0"
b10 #
b10 /
1)
#344000
0)
#346000
b11 1
#348000
b0 .
b1001 #
b1001 /
1)
#350000
0)
#352000
b100 1
#354000
0&
b0 #
b0 /
1)
#356000
0)
#358000
b110111 ,
b101 1
